{
  "ancestors": [
    "android.widget.FrameLayout",
    "android.view.ViewGroup",
    "android.view.View",
    "java.lang.Object"
  ],
  "class": "com.android.internal.policy.PhoneWindow$DecorView",
  "bounds": [
    0,
    0,
    1440,
    2560
  ],
  "clickable": false,
  "children": [
    {
      "text": "Current Location",
      "ancestors": [
        "android.view.View",
        "java.lang.Object"
      ],
      "clickable": false,
      "class": "android.widget.TextView",
      "bounds": [
        210,
        135,
        734,
        228
      ],
      "componentLabel": "Text"
    },
    {
      "iconClass": "menu",
      "ancestors": [
        "android.widget.ImageView",
        "android.view.View",
        "java.lang.Object"
      ],
      "bounds": [
        0,
        84,
        196,
        280
      ],
      "clickable": true,
      "class": "android.widget.ImageButton",
      "componentLabel": "Icon"
    },
    {
      "ancestors": [
        "android.view.View",
        "java.lang.Object"
      ],
      "resource-id": "com.go.abclocal.kabc.android.weather:id/wxLogo",
      "clickable": false,
      "class": "android.widget.ImageView",
      "bounds": [
        53,
        315,
        403,
        665
      ],
      "componentLabel": "Image"
    },
    {
      "ancestors": [
        "android.view.View",
        "java.lang.Object"
      ],
      "resource-id": "com.go.abclocal.kabc.android.weather:id/currentConditionWxImageView",
      "clickable": false,
      "class": "android.widget.ImageView",
      "bounds": [
        545,
        315,
        895,
        665
      ],
      "componentLabel": "Image"
    },
    {
      "text": "45°",
      "resource-id": "com.go.abclocal.kabc.android.weather:id/currentConditionTemp",
      "ancestors": [
        "android.widget.TextView",
        "android.view.View",
        "java.lang.Object"
      ],
      "clickable": false,
      "class": "android.support.v7.widget.AppCompatTextView",
      "bounds": [
        720,
        364,
        1422,
        597
      ],
      "componentLabel": "Text"
    },
    {
      "text": "Mostly cloudy",
      "resource-id": "com.go.abclocal.kabc.android.weather:id/currentConditionWxText",
      "ancestors": [
        "android.widget.TextView",
        "android.view.View",
        "java.lang.Object"
      ],
      "clickable": false,
      "class": "android.support.v7.widget.AppCompatTextView",
      "bounds": [
        720,
        541,
        1422,
        681
      ],
      "componentLabel": "Text"
    },
    {
      "ancestors": [
        "android.view.View",
        "java.lang.Object"
      ],
      "resource-id": "com.go.abclocal.kabc.android.weather:id/accuweatherCredit",
      "clickable": false,
      "class": "android.widget.ImageView",
      "bounds": [
        974,
        280,
        1422,
        319
      ],
      "componentLabel": "Image"
    },
    {
      "ancestors": [
        "android.webkit.WebView",
        "android.widget.AbsoluteLayout",
        "android.view.ViewGroup",
        "android.view.View",
        "java.lang.Object"
      ],
      "bounds": [
        160,
        2217,
        1280,
        2392
      ],
      "clickable": true,
      "class": "tv.freewheel.renderers.html.MRAIDWebView",
      "componentLabel": "Web View"
    },
    {
      "resource-id": "com.go.abclocal.kabc.android.weather:id/row",
      "children": [
        {
          "text": "Sat",
          "resource-id": "com.go.abclocal.kabc.android.weather:id/forecastTitle",
          "ancestors": [
            "android.widget.TextView",
            "android.view.View",
            "java.lang.Object"
          ],
          "clickable": false,
          "class": "android.support.v7.widget.AppCompatTextView",
          "bounds": [
            141,
            862,
            316,
            939
          ],
          "componentLabel": "Text"
        },
        {
          "iconClass": "weather",
          "ancestors": [
            "android.view.View",
            "java.lang.Object"
          ],
          "resource-id": "com.go.abclocal.kabc.android.weather:id/wxIcon",
          "clickable": false,
          "class": "android.widget.ImageView",
          "bounds": [
            439,
            813,
            614,
            988
          ],
          "componentLabel": "Icon"
        },
        {
          "text": "0%",
          "resource-id": "com.go.abclocal.kabc.android.weather:id/popPct",
          "ancestors": [
            "android.widget.TextView",
            "android.view.View",
            "java.lang.Object"
          ],
          "clickable": false,
          "class": "android.support.v7.widget.AppCompatTextView",
          "bounds": [
            737,
            865,
            860,
            936
          ],
          "componentLabel": "Text"
        },
        {
          "text": "46°",
          "resource-id": "com.go.abclocal.kabc.android.weather:id/maxTemp",
          "ancestors": [
            "android.widget.TextView",
            "android.view.View",
            "java.lang.Object"
          ],
          "clickable": false,
          "class": "android.support.v7.widget.AppCompatTextView",
          "bounds": [
            1079,
            844,
            1208,
            956
          ],
          "componentLabel": "Text"
        },
        {
          "text": "/",
          "resource-id": "com.go.abclocal.kabc.android.weather:id/tempSlash",
          "ancestors": [
            "android.widget.TextView",
            "android.view.View",
            "java.lang.Object"
          ],
          "clickable": false,
          "class": "android.support.v7.widget.AppCompatTextView",
          "bounds": [
            1208,
            865,
            1228,
            936
          ],
          "componentLabel": "Text"
        },
        {
          "text": "43°",
          "resource-id": "com.go.abclocal.kabc.android.weather:id/minTemp",
          "ancestors": [
            "android.widget.TextView",
            "android.view.View",
            "java.lang.Object"
          ],
          "clickable": false,
          "class": "android.support.v7.widget.AppCompatTextView",
          "bounds": [
            1228,
            869,
            1298,
            931
          ],
          "componentLabel": "Text"
        }
      ],
      "ancestors": [
        "android.view.ViewGroup",
        "android.view.View",
        "java.lang.Object"
      ],
      "clickable": false,
      "class": "android.widget.LinearLayout",
      "bounds": [
        0,
        804,
        1440,
        997
      ],
      "componentLabel": "List Item"
    },
    {
      "resource-id": "com.go.abclocal.kabc.android.weather:id/row",
      "children": [
        {
          "text": "9 PM",
          "resource-id": "com.go.abclocal.kabc.android.weather:id/forecastTitle",
          "ancestors": [
            "android.widget.TextView",
            "android.view.View",
            "java.lang.Object"
          ],
          "clickable": false,
          "class": "android.support.v7.widget.AppCompatTextView",
          "bounds": [
            85,
            1054,
            260,
            1131
          ],
          "componentLabel": "Text"
        },
        {
          "iconClass": "weather",
          "ancestors": [
            "android.view.View",
            "java.lang.Object"
          ],
          "resource-id": "com.go.abclocal.kabc.android.weather:id/wxIcon",
          "clickable": false,
          "class": "android.widget.ImageView",
          "bounds": [
            327,
            1005,
            502,
            1180
          ],
          "componentLabel": "Icon"
        },
        {
          "text": "0%",
          "resource-id": "com.go.abclocal.kabc.android.weather:id/popPct",
          "ancestors": [
            "android.widget.TextView",
            "android.view.View",
            "java.lang.Object"
          ],
          "clickable": false,
          "class": "android.support.v7.widget.AppCompatTextView",
          "bounds": [
            570,
            1057,
            710,
            1128
          ],
          "componentLabel": "Text"
        },
        {
          "iconClass": "arrow_downward",
          "ancestors": [
            "android.view.View",
            "java.lang.Object"
          ],
          "resource-id": "com.go.abclocal.kabc.android.weather:id/wxWindDirIcon",
          "clickable": false,
          "class": "android.widget.ImageView",
          "bounds": [
            770,
            1032,
            891,
            1153
          ],
          "componentLabel": "Icon"
        },
        {
          "text": "15 mph",
          "resource-id": "com.go.abclocal.kabc.android.weather:id/windSpeed",
          "ancestors": [
            "android.widget.TextView",
            "android.view.View",
            "java.lang.Object"
          ],
          "clickable": false,
          "class": "android.support.v7.widget.AppCompatTextView",
          "bounds": [
            883,
            1057,
            1093,
            1128
          ],
          "componentLabel": "Text"
        },
        {
          "text": "45°",
          "resource-id": "com.go.abclocal.kabc.android.weather:id/maxTemp",
          "ancestors": [
            "android.widget.TextView",
            "android.view.View",
            "java.lang.Object"
          ],
          "clickable": false,
          "class": "android.support.v7.widget.AppCompatTextView",
          "bounds": [
            1161,
            1036,
            1354,
            1148
          ],
          "componentLabel": "Text"
        }
      ],
      "ancestors": [
        "android.view.ViewGroup",
        "android.view.View",
        "java.lang.Object"
      ],
      "clickable": false,
      "class": "android.widget.LinearLayout",
      "bounds": [
        0,
        996,
        1440,
        1189
      ],
      "componentLabel": "List Item"
    },
    {
      "resource-id": "com.go.abclocal.kabc.android.weather:id/row",
      "children": [
        {
          "text": "10 PM",
          "resource-id": "com.go.abclocal.kabc.android.weather:id/forecastTitle",
          "ancestors": [
            "android.widget.TextView",
            "android.view.View",
            "java.lang.Object"
          ],
          "clickable": false,
          "class": "android.support.v7.widget.AppCompatTextView",
          "bounds": [
            85,
            1246,
            260,
            1323
          ],
          "componentLabel": "Text"
        },
        {
          "iconClass": "weather",
          "ancestors": [
            "android.view.View",
            "java.lang.Object"
          ],
          "resource-id": "com.go.abclocal.kabc.android.weather:id/wxIcon",
          "clickable": false,
          "class": "android.widget.ImageView",
          "bounds": [
            327,
            1197,
            502,
            1372
          ],
          "componentLabel": "Icon"
        },
        {
          "text": "0%",
          "resource-id": "com.go.abclocal.kabc.android.weather:id/popPct",
          "ancestors": [
            "android.widget.TextView",
            "android.view.View",
            "java.lang.Object"
          ],
          "clickable": false,
          "class": "android.support.v7.widget.AppCompatTextView",
          "bounds": [
            570,
            1249,
            710,
            1320
          ],
          "componentLabel": "Text"
        },
        {
          "ancestors": [
            "android.view.View",
            "java.lang.Object"
          ],
          "resource-id": "com.go.abclocal.kabc.android.weather:id/wxWindDirIcon",
          "clickable": false,
          "class": "android.widget.ImageView",
          "bounds": [
            763,
            1217,
            898,
            1352
          ],
          "componentLabel": "Image"
        },
        {
          "text": "14 mph",
          "resource-id": "com.go.abclocal.kabc.android.weather:id/windSpeed",
          "ancestors": [
            "android.widget.TextView",
            "android.view.View",
            "java.lang.Object"
          ],
          "clickable": false,
          "class": "android.support.v7.widget.AppCompatTextView",
          "bounds": [
            883,
            1249,
            1093,
            1320
          ],
          "componentLabel": "Text"
        },
        {
          "text": "44°",
          "resource-id": "com.go.abclocal.kabc.android.weather:id/maxTemp",
          "ancestors": [
            "android.widget.TextView",
            "android.view.View",
            "java.lang.Object"
          ],
          "clickable": false,
          "class": "android.support.v7.widget.AppCompatTextView",
          "bounds": [
            1161,
            1228,
            1354,
            1340
          ],
          "componentLabel": "Text"
        }
      ],
      "ancestors": [
        "android.view.ViewGroup",
        "android.view.View",
        "java.lang.Object"
      ],
      "clickable": false,
      "class": "android.widget.LinearLayout",
      "bounds": [
        0,
        1188,
        1440,
        1381
      ],
      "componentLabel": "List Item"
    },
    {
      "resource-id": "com.go.abclocal.kabc.android.weather:id/row",
      "children": [
        {
          "text": "11 PM",
          "resource-id": "com.go.abclocal.kabc.android.weather:id/forecastTitle",
          "ancestors": [
            "android.widget.TextView",
            "android.view.View",
            "java.lang.Object"
          ],
          "clickable": false,
          "class": "android.support.v7.widget.AppCompatTextView",
          "bounds": [
            85,
            1438,
            260,
            1515
          ],
          "componentLabel": "Text"
        },
        {
          "iconClass": "weather",
          "ancestors": [
            "android.view.View",
            "java.lang.Object"
          ],
          "resource-id": "com.go.abclocal.kabc.android.weather:id/wxIcon",
          "clickable": false,
          "class": "android.widget.ImageView",
          "bounds": [
            327,
            1389,
            502,
            1564
          ],
          "componentLabel": "Icon"
        },
        {
          "text": "0%",
          "resource-id": "com.go.abclocal.kabc.android.weather:id/popPct",
          "ancestors": [
            "android.widget.TextView",
            "android.view.View",
            "java.lang.Object"
          ],
          "clickable": false,
          "class": "android.support.v7.widget.AppCompatTextView",
          "bounds": [
            570,
            1441,
            710,
            1512
          ],
          "componentLabel": "Text"
        },
        {
          "ancestors": [
            "android.view.View",
            "java.lang.Object"
          ],
          "resource-id": "com.go.abclocal.kabc.android.weather:id/wxWindDirIcon",
          "clickable": false,
          "class": "android.widget.ImageView",
          "bounds": [
            763,
            1409,
            898,
            1544
          ],
          "componentLabel": "Image"
        },
        {
          "text": "11 mph",
          "resource-id": "com.go.abclocal.kabc.android.weather:id/windSpeed",
          "ancestors": [
            "android.widget.TextView",
            "android.view.View",
            "java.lang.Object"
          ],
          "clickable": false,
          "class": "android.support.v7.widget.AppCompatTextView",
          "bounds": [
            883,
            1441,
            1093,
            1512
          ],
          "componentLabel": "Text"
        },
        {
          "text": "43°",
          "resource-id": "com.go.abclocal.kabc.android.weather:id/maxTemp",
          "ancestors": [
            "android.widget.TextView",
            "android.view.View",
            "java.lang.Object"
          ],
          "clickable": false,
          "class": "android.support.v7.widget.AppCompatTextView",
          "bounds": [
            1161,
            1420,
            1354,
            1532
          ],
          "componentLabel": "Text"
        }
      ],
      "ancestors": [
        "android.view.ViewGroup",
        "android.view.View",
        "java.lang.Object"
      ],
      "clickable": false,
      "class": "android.widget.LinearLayout",
      "bounds": [
        0,
        1380,
        1440,
        1573
      ],
      "componentLabel": "List Item"
    },
    {
      "resource-id": "com.go.abclocal.kabc.android.weather:id/row",
      "children": [
        {
          "text": "Sun",
          "resource-id": "com.go.abclocal.kabc.android.weather:id/forecastTitle",
          "ancestors": [
            "android.widget.TextView",
            "android.view.View",
            "java.lang.Object"
          ],
          "clickable": false,
          "class": "android.support.v7.widget.AppCompatTextView",
          "bounds": [
            141,
            1630,
            316,
            1707
          ],
          "componentLabel": "Text"
        },
        {
          "iconClass": "weather",
          "ancestors": [
            "android.view.View",
            "java.lang.Object"
          ],
          "resource-id": "com.go.abclocal.kabc.android.weather:id/wxIcon",
          "clickable": false,
          "class": "android.widget.ImageView",
          "bounds": [
            439,
            1581,
            614,
            1756
          ],
          "componentLabel": "Icon"
        },
        {
          "text": "0%",
          "resource-id": "com.go.abclocal.kabc.android.weather:id/popPct",
          "ancestors": [
            "android.widget.TextView",
            "android.view.View",
            "java.lang.Object"
          ],
          "clickable": false,
          "class": "android.support.v7.widget.AppCompatTextView",
          "bounds": [
            737,
            1633,
            860,
            1704
          ],
          "componentLabel": "Text"
        },
        {
          "text": "55°",
          "resource-id": "com.go.abclocal.kabc.android.weather:id/maxTemp",
          "ancestors": [
            "android.widget.TextView",
            "android.view.View",
            "java.lang.Object"
          ],
          "clickable": false,
          "class": "android.support.v7.widget.AppCompatTextView",
          "bounds": [
            1079,
            1612,
            1208,
            1724
          ],
          "componentLabel": "Text"
        },
        {
          "text": "/",
          "resource-id": "com.go.abclocal.kabc.android.weather:id/tempSlash",
          "ancestors": [
            "android.widget.TextView",
            "android.view.View",
            "java.lang.Object"
          ],
          "clickable": false,
          "class": "android.support.v7.widget.AppCompatTextView",
          "bounds": [
            1208,
            1633,
            1228,
            1704
          ],
          "componentLabel": "Text"
        },
        {
          "text": "41°",
          "resource-id": "com.go.abclocal.kabc.android.weather:id/minTemp",
          "ancestors": [
            "android.widget.TextView",
            "android.view.View",
            "java.lang.Object"
          ],
          "clickable": false,
          "class": "android.support.v7.widget.AppCompatTextView",
          "bounds": [
            1228,
            1637,
            1298,
            1699
          ],
          "componentLabel": "Text"
        }
      ],
      "ancestors": [
        "android.view.ViewGroup",
        "android.view.View",
        "java.lang.Object"
      ],
      "clickable": false,
      "class": "android.widget.LinearLayout",
      "bounds": [
        0,
        1572,
        1440,
        1765
      ],
      "componentLabel": "List Item"
    },
    {
      "resource-id": "com.go.abclocal.kabc.android.weather:id/row",
      "children": [
        {
          "text": "12 AM",
          "resource-id": "com.go.abclocal.kabc.android.weather:id/forecastTitle",
          "ancestors": [
            "android.widget.TextView",
            "android.view.View",
            "java.lang.Object"
          ],
          "clickable": false,
          "class": "android.support.v7.widget.AppCompatTextView",
          "bounds": [
            85,
            1822,
            260,
            1899
          ],
          "componentLabel": "Text"
        },
        {
          "iconClass": "weather",
          "ancestors": [
            "android.view.View",
            "java.lang.Object"
          ],
          "resource-id": "com.go.abclocal.kabc.android.weather:id/wxIcon",
          "clickable": false,
          "class": "android.widget.ImageView",
          "bounds": [
            327,
            1773,
            502,
            1948
          ],
          "componentLabel": "Icon"
        },
        {
          "text": "0%",
          "resource-id": "com.go.abclocal.kabc.android.weather:id/popPct",
          "ancestors": [
            "android.widget.TextView",
            "android.view.View",
            "java.lang.Object"
          ],
          "clickable": false,
          "class": "android.support.v7.widget.AppCompatTextView",
          "bounds": [
            570,
            1825,
            710,
            1896
          ],
          "componentLabel": "Text"
        },
        {
          "ancestors": [
            "android.view.View",
            "java.lang.Object"
          ],
          "resource-id": "com.go.abclocal.kabc.android.weather:id/wxWindDirIcon",
          "clickable": false,
          "class": "android.widget.ImageView",
          "bounds": [
            763,
            1793,
            898,
            1928
          ],
          "componentLabel": "Image"
        },
        {
          "text": "10 mph",
          "resource-id": "com.go.abclocal.kabc.android.weather:id/windSpeed",
          "ancestors": [
            "android.widget.TextView",
            "android.view.View",
            "java.lang.Object"
          ],
          "clickable": false,
          "class": "android.support.v7.widget.AppCompatTextView",
          "bounds": [
            883,
            1825,
            1093,
            1896
          ],
          "componentLabel": "Text"
        },
        {
          "text": "43°",
          "resource-id": "com.go.abclocal.kabc.android.weather:id/maxTemp",
          "ancestors": [
            "android.widget.TextView",
            "android.view.View",
            "java.lang.Object"
          ],
          "clickable": false,
          "class": "android.support.v7.widget.AppCompatTextView",
          "bounds": [
            1161,
            1804,
            1354,
            1916
          ],
          "componentLabel": "Text"
        }
      ],
      "ancestors": [
        "android.view.ViewGroup",
        "android.view.View",
        "java.lang.Object"
      ],
      "clickable": false,
      "class": "android.widget.LinearLayout",
      "bounds": [
        0,
        1764,
        1440,
        1957
      ],
      "componentLabel": "List Item"
    },
    {
      "resource-id": "com.go.abclocal.kabc.android.weather:id/row",
      "children": [
        {
          "text": "1 AM",
          "resource-id": "com.go.abclocal.kabc.android.weather:id/forecastTitle",
          "ancestors": [
            "android.widget.TextView",
            "android.view.View",
            "java.lang.Object"
          ],
          "clickable": false,
          "class": "android.support.v7.widget.AppCompatTextView",
          "bounds": [
            85,
            2014,
            260,
            2091
          ],
          "componentLabel": "Text"
        },
        {
          "iconClass": "weather",
          "ancestors": [
            "android.view.View",
            "java.lang.Object"
          ],
          "resource-id": "com.go.abclocal.kabc.android.weather:id/wxIcon",
          "clickable": false,
          "class": "android.widget.ImageView",
          "bounds": [
            327,
            1965,
            502,
            2140
          ],
          "componentLabel": "Icon"
        },
        {
          "text": "0%",
          "resource-id": "com.go.abclocal.kabc.android.weather:id/popPct",
          "ancestors": [
            "android.widget.TextView",
            "android.view.View",
            "java.lang.Object"
          ],
          "clickable": false,
          "class": "android.support.v7.widget.AppCompatTextView",
          "bounds": [
            570,
            2017,
            710,
            2088
          ],
          "componentLabel": "Text"
        },
        {
          "ancestors": [
            "android.view.View",
            "java.lang.Object"
          ],
          "resource-id": "com.go.abclocal.kabc.android.weather:id/wxWindDirIcon",
          "clickable": false,
          "class": "android.widget.ImageView",
          "bounds": [
            759,
            1981,
            902,
            2124
          ],
          "componentLabel": "Image"
        },
        {
          "text": "9 mph",
          "resource-id": "com.go.abclocal.kabc.android.weather:id/windSpeed",
          "ancestors": [
            "android.widget.TextView",
            "android.view.View",
            "java.lang.Object"
          ],
          "clickable": false,
          "class": "android.support.v7.widget.AppCompatTextView",
          "bounds": [
            883,
            2017,
            1093,
            2088
          ],
          "componentLabel": "Text"
        },
        {
          "text": "42°",
          "resource-id": "com.go.abclocal.kabc.android.weather:id/maxTemp",
          "ancestors": [
            "android.widget.TextView",
            "android.view.View",
            "java.lang.Object"
          ],
          "clickable": false,
          "class": "android.support.v7.widget.AppCompatTextView",
          "bounds": [
            1161,
            1996,
            1354,
            2108
          ],
          "componentLabel": "Text"
        }
      ],
      "ancestors": [
        "android.view.ViewGroup",
        "android.view.View",
        "java.lang.Object"
      ],
      "clickable": false,
      "class": "android.widget.LinearLayout",
      "bounds": [
        0,
        1956,
        1440,
        2149
      ],
      "componentLabel": "List Item"
    },
    {
      "resource-id": "com.go.abclocal.kabc.android.weather:id/row",
      "children": [
        {
          "text": "2 AM",
          "resource-id": "com.go.abclocal.kabc.android.weather:id/forecastTitle",
          "ancestors": [
            "android.widget.TextView",
            "android.view.View",
            "java.lang.Object"
          ],
          "clickable": false,
          "class": "android.support.v7.widget.AppCompatTextView",
          "bounds": [
            85,
            2206,
            260,
            2217
          ],
          "componentLabel": "Text"
        },
        {
          "ancestors": [
            "android.view.View",
            "java.lang.Object"
          ],
          "resource-id": "com.go.abclocal.kabc.android.weather:id/wxIcon",
          "clickable": false,
          "class": "android.widget.ImageView",
          "bounds": [
            327,
            2157,
            502,
            2217
          ],
          "componentLabel": "Image"
        },
        {
          "text": "0%",
          "resource-id": "com.go.abclocal.kabc.android.weather:id/popPct",
          "ancestors": [
            "android.widget.TextView",
            "android.view.View",
            "java.lang.Object"
          ],
          "clickable": false,
          "class": "android.support.v7.widget.AppCompatTextView",
          "bounds": [
            570,
            2209,
            710,
            2217
          ],
          "componentLabel": "Text"
        },
        {
          "ancestors": [
            "android.view.View",
            "java.lang.Object"
          ],
          "resource-id": "com.go.abclocal.kabc.android.weather:id/wxWindDirIcon",
          "clickable": false,
          "class": "android.widget.ImageView",
          "bounds": [
            757,
            2171,
            904,
            2217
          ],
          "componentLabel": "Image"
        },
        {
          "text": "9 mph",
          "resource-id": "com.go.abclocal.kabc.android.weather:id/windSpeed",
          "ancestors": [
            "android.widget.TextView",
            "android.view.View",
            "java.lang.Object"
          ],
          "clickable": false,
          "class": "android.support.v7.widget.AppCompatTextView",
          "bounds": [
            883,
            2209,
            1093,
            2217
          ],
          "componentLabel": "Text"
        },
        {
          "text": "42°",
          "resource-id": "com.go.abclocal.kabc.android.weather:id/maxTemp",
          "ancestors": [
            "android.widget.TextView",
            "android.view.View",
            "java.lang.Object"
          ],
          "clickable": false,
          "class": "android.support.v7.widget.AppCompatTextView",
          "bounds": [
            1161,
            2188,
            1354,
            2217
          ],
          "componentLabel": "Text"
        }
      ],
      "ancestors": [
        "android.view.ViewGroup",
        "android.view.View",
        "java.lang.Object"
      ],
      "clickable": false,
      "class": "android.widget.LinearLayout",
      "bounds": [
        0,
        2148,
        1440,
        2217
      ],
      "componentLabel": "List Item"
    },
    {
      "text": "Live Radar",
      "resource-id": "com.go.abclocal.kabc.android.weather:id/button1",
      "ancestors": [
        "android.widget.Button",
        "android.widget.TextView",
        "android.view.View",
        "java.lang.Object"
      ],
      "clickable": true,
      "class": "android.support.v7.widget.AppCompatButton",
      "bounds": [
        0,
        681,
        360,
        804
      ],
      "componentLabel": "Text Button"
    },
    {
      "text": "7 Day",
      "resource-id": "com.go.abclocal.kabc.android.weather:id/button2",
      "ancestors": [
        "android.widget.Button",
        "android.widget.TextView",
        "android.view.View",
        "java.lang.Object"
      ],
      "clickable": true,
      "class": "android.support.v7.widget.AppCompatButton",
      "bounds": [
        360,
        681,
        720,
        804
      ],
      "componentLabel": "Text Button"
    },
    {
      "text": "Hourly",
      "resource-id": "com.go.abclocal.kabc.android.weather:id/button3",
      "ancestors": [
        "android.widget.Button",
        "android.widget.TextView",
        "android.view.View",
        "java.lang.Object"
      ],
      "clickable": true,
      "class": "android.support.v7.widget.AppCompatButton",
      "bounds": [
        720,
        681,
        1080,
        804
      ],
      "componentLabel": "Text Button",
      "textButtonClass": "hourly"
    },
    {
      "resource-id": "com.go.abclocal.kabc.android.weather:id/button4",
      "children": [
        {
          "iconClass": "warning",
          "ancestors": [
            "android.view.View",
            "java.lang.Object"
          ],
          "bounds": [
            1289,
            681,
            1440,
            804
          ],
          "clickable": false,
          "class": "android.widget.ImageView",
          "componentLabel": "Icon"
        },
        {
          "ancestors": [
            "android.view.View",
            "java.lang.Object"
          ],
          "text": "ALERTS",
          "bounds": [
            1122,
            712,
            1260,
            764
          ],
          "clickable": false,
          "class": "android.widget.TextView",
          "componentLabel": "Text"
        }
      ],
      "ancestors": [
        "com.wdtinc.android.whitelabel.gui.WHTAlertBadgeButton",
        "android.widget.RelativeLayout",
        "android.view.ViewGroup",
        "android.view.View",
        "java.lang.Object"
      ],
      "clickable": true,
      "class": "com.wdtinc.android.whitelabel.gui.WHTTabbedAlertBadgeButton",
      "bounds": [
        1080,
        681,
        1440,
        804
      ],
      "componentLabel": "Image"
    }
  ]
}