{
  "ancestors": [
    "android.widget.FrameLayout",
    "android.view.ViewGroup",
    "android.view.View",
    "java.lang.Object"
  ],
  "class": "com.android.internal.policy.PhoneWindow$DecorView",
  "bounds": [
    0,
    0,
    1440,
    2560
  ],
  "clickable": false,
  "children": [
    {
      "resource-id": "com.mercariapp.mercari:id/headerbar",
      "children": [
        {
          "resource-id": "com.mercariapp.mercari:id/toolbar_actionbar",
          "children": [
            {
              "iconClass": "menu",
              "ancestors": [
                "android.widget.ImageView",
                "android.view.View",
                "java.lang.Object"
              ],
              "bounds": [
                0,
                86,
                196,
                277
              ],
              "clickable": true,
              "class": "android.widget.ImageButton",
              "componentLabel": "Icon"
            },
            {
              "ancestors": [
                "android.view.View",
                "java.lang.Object"
              ],
              "bounds": [
                196,
                144,
                546,
                214
              ],
              "clickable": false,
              "class": "android.widget.ImageView",
              "componentLabel": "Image"
            },
            {
              "iconClass": "search",
              "ancestors": [
                "android.widget.ImageView",
                "android.view.View",
                "java.lang.Object"
              ],
              "resource-id": "com.mercariapp.mercari:id/img_main",
              "clickable": false,
              "class": "android.support.v7.widget.n",
              "bounds": [
                861,
                139,
                984,
                223
              ],
              "componentLabel": "Icon"
            },
            {
              "iconClass": "notifications",
              "ancestors": [
                "android.widget.ImageView",
                "android.view.View",
                "java.lang.Object"
              ],
              "resource-id": "com.mercariapp.mercari:id/img_main",
              "clickable": false,
              "class": "android.support.v7.widget.n",
              "bounds": [
                1068,
                139,
                1191,
                223
              ],
              "componentLabel": "Icon"
            },
            {
              "text": "1",
              "resource-id": "com.mercariapp.mercari:id/img_count",
              "ancestors": [
                "android.widget.TextView",
                "android.view.View",
                "java.lang.Object"
              ],
              "clickable": false,
              "class": "android.support.v7.widget.AppCompatTextView",
              "bounds": [
                1135,
                107,
                1191,
                164
              ],
              "componentLabel": "Text"
            },
            {
              "iconClass": "check",
              "ancestors": [
                "android.widget.ImageView",
                "android.view.View",
                "java.lang.Object"
              ],
              "resource-id": "com.mercariapp.mercari:id/img_main",
              "clickable": false,
              "class": "android.support.v7.widget.n",
              "bounds": [
                1275,
                139,
                1398,
                223
              ],
              "componentLabel": "Icon"
            }
          ],
          "ancestors": [
            "android.view.ViewGroup",
            "android.view.View",
            "java.lang.Object"
          ],
          "clickable": false,
          "class": "android.support.v7.widget.Toolbar",
          "bounds": [
            0,
            84,
            1440,
            280
          ],
          "componentLabel": "Toolbar"
        }
      ],
      "ancestors": [
        "android.view.ViewGroup",
        "android.view.View",
        "java.lang.Object"
      ],
      "clickable": false,
      "class": "android.widget.LinearLayout",
      "bounds": [
        0,
        84,
        1440,
        2392
      ],
      "componentLabel": "Drawer"
    },
    {
      "ancestors": [
        "android.view.View",
        "java.lang.Object"
      ],
      "resource-id": "com.mercariapp.mercari:id/btnCamera",
      "clickable": true,
      "class": "android.widget.ImageView",
      "bounds": [
        1146,
        2098,
        1440,
        2392
      ],
      "componentLabel": "Image"
    },
    {
      "text": "ELECTRONICS",
      "ancestors": [
        "android.view.View",
        "java.lang.Object"
      ],
      "clickable": true,
      "class": "android.widget.TextView",
      "bounds": [
        0,
        315,
        315,
        381
      ],
      "componentLabel": "Text Button"
    },
    {
      "text": "ALL",
      "ancestors": [
        "android.view.View",
        "java.lang.Object"
      ],
      "clickable": false,
      "class": "android.widget.TextView",
      "bounds": [
        678,
        315,
        762,
        381
      ],
      "componentLabel": "Text"
    },
    {
      "text": "WOMEN",
      "ancestors": [
        "android.view.View",
        "java.lang.Object"
      ],
      "clickable": true,
      "class": "android.widget.TextView",
      "bounds": [
        1257,
        315,
        1440,
        381
      ],
      "componentLabel": "Text Button"
    },
    {
      "text": "New Items",
      "ancestors": [
        "android.widget.TextView",
        "android.view.View",
        "java.lang.Object"
      ],
      "clickable": true,
      "class": "android.support.v7.widget.AppCompatTextView",
      "bounds": [
        538,
        472,
        901,
        574
      ],
      "componentLabel": "Text Button"
    },
    {
      "ancestors": [
        "android.view.ViewGroup",
        "android.view.View",
        "java.lang.Object"
      ],
      "class": "android.widget.RelativeLayout",
      "bounds": [
        0,
        437,
        1440,
        1077
      ],
      "clickable": false,
      "children": [
        {
          "ancestors": [
            "com.kouzoh.mercari.ui.CachedImageView",
            "android.widget.ImageView",
            "android.view.View",
            "java.lang.Object"
          ],
          "resource-id": "com.mercariapp.mercari:id/banner_image",
          "clickable": false,
          "class": "com.kouzoh.mercari.ui.BannerImageView",
          "bounds": [
            0,
            437,
            1440,
            1077
          ],
          "componentLabel": "Image"
        },
        {
          "ancestors": [
            "android.view.View",
            "java.lang.Object"
          ],
          "resource-id": "com.mercariapp.mercari:id/ripple_view",
          "clickable": true,
          "class": "android.widget.ImageView",
          "bounds": [
            0,
            437,
            1440,
            1077
          ],
          "componentLabel": "Image"
        }
      ],
      "componentLabel": "List Item"
    },
    {
      "ancestors": [
        "android.view.ViewGroup",
        "android.view.View",
        "java.lang.Object"
      ],
      "class": "android.widget.LinearLayout",
      "bounds": [
        0,
        1077,
        1440,
        1557
      ],
      "clickable": false,
      "children": [
        {
          "ancestors": [
            "android.widget.ImageView",
            "android.view.View",
            "java.lang.Object"
          ],
          "resource-id": "com.mercariapp.mercari:id/thumb",
          "clickable": false,
          "class": "com.kouzoh.mercari.ui.CachedImageView",
          "bounds": [
            14,
            1091,
            466,
            1543
          ],
          "componentLabel": "Image"
        },
        {
          "text": "$29",
          "resource-id": "com.mercariapp.mercari:id/price_text",
          "ancestors": [
            "android.view.View",
            "java.lang.Object"
          ],
          "clickable": false,
          "class": "android.widget.TextView",
          "bounds": [
            14,
            1449,
            133,
            1543
          ],
          "componentLabel": "Text"
        },
        {
          "ancestors": [
            "android.widget.ImageView",
            "android.view.View",
            "java.lang.Object"
          ],
          "resource-id": "com.mercariapp.mercari:id/thumb",
          "clickable": false,
          "class": "com.kouzoh.mercari.ui.CachedImageView",
          "bounds": [
            494,
            1091,
            946,
            1543
          ],
          "componentLabel": "Image"
        },
        {
          "text": "$7",
          "resource-id": "com.mercariapp.mercari:id/price_text",
          "ancestors": [
            "android.view.View",
            "java.lang.Object"
          ],
          "clickable": false,
          "class": "android.widget.TextView",
          "bounds": [
            494,
            1449,
            585,
            1543
          ],
          "componentLabel": "Text"
        },
        {
          "ancestors": [
            "android.widget.ImageView",
            "android.view.View",
            "java.lang.Object"
          ],
          "resource-id": "com.mercariapp.mercari:id/thumb",
          "clickable": false,
          "class": "com.kouzoh.mercari.ui.CachedImageView",
          "bounds": [
            974,
            1091,
            1426,
            1543
          ],
          "componentLabel": "Image"
        },
        {
          "text": "$4",
          "resource-id": "com.mercariapp.mercari:id/price_text",
          "ancestors": [
            "android.view.View",
            "java.lang.Object"
          ],
          "clickable": false,
          "class": "android.widget.TextView",
          "bounds": [
            974,
            1449,
            1065,
            1543
          ],
          "componentLabel": "Text"
        }
      ],
      "componentLabel": "List Item"
    },
    {
      "ancestors": [
        "android.view.ViewGroup",
        "android.view.View",
        "java.lang.Object"
      ],
      "class": "android.widget.LinearLayout",
      "bounds": [
        0,
        1557,
        1440,
        2037
      ],
      "clickable": false,
      "children": [
        {
          "ancestors": [
            "android.widget.ImageView",
            "android.view.View",
            "java.lang.Object"
          ],
          "resource-id": "com.mercariapp.mercari:id/thumb",
          "clickable": false,
          "class": "com.kouzoh.mercari.ui.CachedImageView",
          "bounds": [
            14,
            1571,
            466,
            2023
          ],
          "componentLabel": "Image"
        },
        {
          "text": "$45",
          "resource-id": "com.mercariapp.mercari:id/price_text",
          "ancestors": [
            "android.view.View",
            "java.lang.Object"
          ],
          "clickable": false,
          "class": "android.widget.TextView",
          "bounds": [
            14,
            1929,
            133,
            2023
          ],
          "componentLabel": "Text"
        },
        {
          "ancestors": [
            "android.widget.ImageView",
            "android.view.View",
            "java.lang.Object"
          ],
          "resource-id": "com.mercariapp.mercari:id/thumb",
          "clickable": false,
          "class": "com.kouzoh.mercari.ui.CachedImageView",
          "bounds": [
            494,
            1571,
            946,
            2023
          ],
          "componentLabel": "Image"
        },
        {
          "text": "$4",
          "resource-id": "com.mercariapp.mercari:id/price_text",
          "ancestors": [
            "android.view.View",
            "java.lang.Object"
          ],
          "clickable": false,
          "class": "android.widget.TextView",
          "bounds": [
            494,
            1929,
            585,
            2023
          ],
          "componentLabel": "Text"
        },
        {
          "ancestors": [
            "android.widget.ImageView",
            "android.view.View",
            "java.lang.Object"
          ],
          "resource-id": "com.mercariapp.mercari:id/thumb",
          "clickable": false,
          "class": "com.kouzoh.mercari.ui.CachedImageView",
          "bounds": [
            974,
            1571,
            1426,
            2023
          ],
          "componentLabel": "Image"
        },
        {
          "text": "$7",
          "resource-id": "com.mercariapp.mercari:id/price_text",
          "ancestors": [
            "android.view.View",
            "java.lang.Object"
          ],
          "clickable": false,
          "class": "android.widget.TextView",
          "bounds": [
            974,
            1929,
            1065,
            2023
          ],
          "componentLabel": "Text"
        }
      ],
      "componentLabel": "List Item"
    },
    {
      "ancestors": [
        "android.view.ViewGroup",
        "android.view.View",
        "java.lang.Object"
      ],
      "class": "android.widget.LinearLayout",
      "bounds": [
        0,
        2037,
        1440,
        2392
      ],
      "clickable": false,
      "children": [
        {
          "ancestors": [
            "android.widget.ImageView",
            "android.view.View",
            "java.lang.Object"
          ],
          "resource-id": "com.mercariapp.mercari:id/thumb",
          "clickable": false,
          "class": "com.kouzoh.mercari.ui.CachedImageView",
          "bounds": [
            14,
            2051,
            466,
            2392
          ],
          "componentLabel": "Image"
        },
        {
          "ancestors": [
            "android.widget.ImageView",
            "android.view.View",
            "java.lang.Object"
          ],
          "resource-id": "com.mercariapp.mercari:id/thumb",
          "clickable": false,
          "class": "com.kouzoh.mercari.ui.CachedImageView",
          "bounds": [
            494,
            2051,
            946,
            2392
          ],
          "componentLabel": "Image"
        },
        {
          "ancestors": [
            "android.widget.ImageView",
            "android.view.View",
            "java.lang.Object"
          ],
          "resource-id": "com.mercariapp.mercari:id/thumb",
          "clickable": false,
          "class": "com.kouzoh.mercari.ui.CachedImageView",
          "bounds": [
            974,
            2051,
            1426,
            2392
          ],
          "componentLabel": "Image"
        }
      ],
      "componentLabel": "List Item"
    }
  ]
}