{
  "ancestors": [
    "android.widget.FrameLayout",
    "android.view.ViewGroup",
    "android.view.View",
    "java.lang.Object"
  ],
  "class": "com.android.internal.policy.PhoneWindow$DecorView",
  "bounds": [
    0,
    0,
    1440,
    2560
  ],
  "clickable": false,
  "children": [
    {
      "resource-id": "com.testa.databot:id/action_bar_container",
      "children": [
        {
          "text": "Settings",
          "ancestors": [
            "android.view.View",
            "java.lang.Object"
          ],
          "clickable": false,
          "class": "android.widget.TextView",
          "bounds": [
            378,
            135,
            637,
            228
          ],
          "componentLabel": "Text"
        },
        {
          "iconClass": "arrow_backward",
          "ancestors": [
            "android.widget.ImageView",
            "android.view.View",
            "java.lang.Object"
          ],
          "bounds": [
            0,
            84,
            196,
            280
          ],
          "clickable": true,
          "class": "android.widget.ImageButton",
          "componentLabel": "Icon"
        },
        {
          "ancestors": [
            "android.view.View",
            "java.lang.Object"
          ],
          "bounds": [
            196,
            98,
            364,
            266
          ],
          "clickable": false,
          "class": "android.widget.ImageView",
          "componentLabel": "Image"
        },
        {
          "ancestors": [
            "android.support.v7.widget.LinearLayoutCompat",
            "android.view.ViewGroup",
            "android.view.View",
            "java.lang.Object"
          ],
          "class": "android.support.v7.widget.ScrollingTabContainerView$TabView",
          "bounds": [
            54,
            280,
            495,
            448
          ],
          "clickable": true,
          "componentLabel": "Text Button",
          "text": "ACCOUNT"
        },
        {
          "ancestors": [
            "android.support.v7.widget.LinearLayoutCompat",
            "android.view.ViewGroup",
            "android.view.View",
            "java.lang.Object"
          ],
          "class": "android.support.v7.widget.ScrollingTabContainerView$TabView",
          "bounds": [
            499,
            280,
            940,
            448
          ],
          "clickable": true,
          "componentLabel": "Text Button",
          "text": "MODULES"
        },
        {
          "ancestors": [
            "android.support.v7.widget.LinearLayoutCompat",
            "android.view.ViewGroup",
            "android.view.View",
            "java.lang.Object"
          ],
          "class": "android.support.v7.widget.ScrollingTabContainerView$TabView",
          "bounds": [
            944,
            280,
            1385,
            448
          ],
          "clickable": true,
          "componentLabel": "Text Button",
          "text": "JOKES"
        }
      ],
      "ancestors": [
        "android.widget.FrameLayout",
        "android.view.ViewGroup",
        "android.view.View",
        "java.lang.Object"
      ],
      "clickable": false,
      "class": "android.support.v7.widget.ActionBarContainer",
      "bounds": [
        0,
        84,
        1440,
        448
      ],
      "componentLabel": "Toolbar"
    },
    {
      "text": "Customize services offered by Databot",
      "resource-id": "com.testa.databot:id/lblSpiegazioneModuli",
      "ancestors": [
        "android.widget.TextView",
        "android.view.View",
        "java.lang.Object"
      ],
      "clickable": false,
      "class": "android.support.v7.widget.AppCompatTextView",
      "bounds": [
        112,
        560,
        1272,
        636
      ],
      "componentLabel": "Text"
    },
    {
      "text": "PRESENTATION - THEME MODULES",
      "resource-id": "com.testa.databot:id/lblEtichettaSlideShow",
      "ancestors": [
        "android.widget.TextView",
        "android.view.View",
        "java.lang.Object"
      ],
      "clickable": false,
      "class": "android.support.v7.widget.AppCompatTextView",
      "bounds": [
        112,
        692,
        1272,
        758
      ],
      "componentLabel": "Text"
    },
    {
      "text": "Customize the number of words that Databot can use at maximum, to prepare presentations in thematic modules (Person, Character, ...).",
      "resource-id": "com.testa.databot:id/lblDescrizioneSlideShow",
      "ancestors": [
        "android.widget.TextView",
        "android.view.View",
        "java.lang.Object"
      ],
      "clickable": false,
      "class": "android.support.v7.widget.AppCompatTextView",
      "bounds": [
        112,
        758,
        1272,
        938
      ],
      "componentLabel": "Text"
    },
    {
      "text": "Customize number of images that DataBot can uses inside presentations. Decrease to improve performance.",
      "resource-id": "com.testa.databot:id/lblDescrizioneIMGSlideShow",
      "ancestors": [
        "android.widget.TextView",
        "android.view.View",
        "java.lang.Object"
      ],
      "clickable": false,
      "class": "android.support.v7.widget.AppCompatTextView",
      "bounds": [
        112,
        1182,
        1272,
        1362
      ],
      "componentLabel": "Text"
    },
    {
      "text": "FAST RESPONSE BEHAVIOR",
      "resource-id": "com.testa.databot:id/lblEtichettaRispostaVeloce",
      "ancestors": [
        "android.widget.TextView",
        "android.view.View",
        "java.lang.Object"
      ],
      "clickable": false,
      "class": "android.support.v7.widget.AppCompatTextView",
      "bounds": [
        112,
        1606,
        725,
        1672
      ],
      "componentLabel": "Text"
    },
    {
      "text": "By default following a short answer, the droid if further relevant informations are available leads you to the page answer. You can change this behavior by disabling this option.",
      "resource-id": "com.testa.databot:id/lblDescrizioneRispostaVeloce",
      "ancestors": [
        "android.widget.TextView",
        "android.view.View",
        "java.lang.Object"
      ],
      "clickable": false,
      "class": "android.support.v7.widget.AppCompatTextView",
      "bounds": [
        112,
        1672,
        1272,
        1909
      ],
      "componentLabel": "Text"
    },
    {
      "text": "ON",
      "resource-id": "com.testa.databot:id/chkbxRispostaVeloce",
      "ancestors": [
        "android.widget.CheckBox",
        "android.widget.CompoundButton",
        "android.widget.Button",
        "android.widget.TextView",
        "android.view.View",
        "java.lang.Object"
      ],
      "clickable": true,
      "class": "android.support.v7.widget.AppCompatCheckBox",
      "bounds": [
        112,
        1965,
        1272,
        2077
      ],
      "componentLabel": "Text Button"
    },
    {
      "text": "save",
      "resource-id": "com.testa.databot:id/bttnSalvaModuli",
      "ancestors": [
        "android.widget.Button",
        "android.widget.TextView",
        "android.view.View",
        "java.lang.Object"
      ],
      "clickable": true,
      "class": "android.support.v7.widget.AppCompatButton",
      "bounds": [
        112,
        2189,
        1272,
        2280
      ],
      "componentLabel": "Text Button",
      "textButtonClass": "save"
    },
    {
      "text": "WORDS LIMIT:",
      "resource-id": "com.testa.databot:id/lblEtichettaNumParoleSlideShow",
      "ancestors": [
        "android.widget.TextView",
        "android.view.View",
        "java.lang.Object"
      ],
      "clickable": false,
      "class": "android.support.v7.widget.AppCompatTextView",
      "bounds": [
        112,
        1002,
        803,
        1068
      ],
      "componentLabel": "Text"
    },
    {
      "text": "800",
      "resource-id": "com.testa.databot:id/txtNumParoleSlideShow",
      "ancestors": [
        "android.widget.EditText",
        "android.widget.TextView",
        "android.view.View",
        "java.lang.Object"
      ],
      "clickable": true,
      "class": "android.support.v7.widget.AppCompatEditText",
      "bounds": [
        803,
        994,
        1272,
        1070
      ],
      "componentLabel": "Input"
    },
    {
      "text": "IMAGES LIMIT:",
      "resource-id": "com.testa.databot:id/lblEtichettaNumIMGSlideShow",
      "ancestors": [
        "android.widget.TextView",
        "android.view.View",
        "java.lang.Object"
      ],
      "clickable": false,
      "class": "android.support.v7.widget.AppCompatTextView",
      "bounds": [
        112,
        1426,
        630,
        1492
      ],
      "componentLabel": "Text"
    },
    {
      "text": "10",
      "resource-id": "com.testa.databot:id/txtNumIMGSlideShow",
      "ancestors": [
        "android.widget.EditText",
        "android.widget.TextView",
        "android.view.View",
        "java.lang.Object"
      ],
      "clickable": true,
      "class": "android.support.v7.widget.AppCompatEditText",
      "bounds": [
        630,
        1418,
        1272,
        1494
      ],
      "componentLabel": "Input"
    }
  ]
}